cs/sqlalchemy_utils.py
cs_sqlalchemy_utils-20250308.dist-info/WHEEL
cs_sqlalchemy_utils-20250308.dist-info/METADATA
cs_sqlalchemy_utils-20250308.dist-info/RECORD
