Metadata-Version: 2.4
Name: cs-sqlalchemy_utils
Version: 20250308
Summary: Assorted utility functions to support working with SQLAlchemy.
Keywords: python2,python3
Author-email: Cameron Simpson <cs@cskk.id.au>
Classifier: Programming Language :: Python
Classifier: Programming Language :: Python :: 3
Classifier: Topic :: Database
Classifier: Development Status :: 4 - Beta
Classifier: Intended Audience :: Developers
Classifier: Operating System :: OS Independent
Classifier: License :: OSI Approved :: GNU General Public License v3 or later (GPLv3+)
Requires-Dist: cs.context>=20250306
Requires-Dist: cs.deco>=20250306
Requires-Dist: cs.fileutils>=20250103
Requires-Dist: cs.lex>=20250103
Requires-Dist: cs.logutils>=20250306
Requires-Dist: cs.pfx>=20250308
Requires-Dist: cs.py.func>=20240630
Requires-Dist: cs.resources>=20250306
Requires-Dist: cs.threads>=20250306
Requires-Dist: icontract
Requires-Dist: sqlalchemy>=2.0
Requires-Dist: typeguard
Project-URL: MonoRepo Commits, https://bitbucket.org/cameron_simpson/css/commits/branch/main
Project-URL: Monorepo Git Mirror, https://github.com/cameron-simpson/css
Project-URL: Monorepo Hg/Mercurial Mirror, https://hg.sr.ht/~cameron-simpson/css
Project-URL: Source, https://github.com/cameron-simpson/css/blob/main/lib/python/cs/sqlalchemy_utils.py
